aether/__init__.py
aether_framework_sdk-0.1.4.dist-info/METADATA
aether_framework_sdk-0.1.4.dist-info/WHEEL
aether_framework_sdk-0.1.4.dist-info/top_level.txt
aether_framework_sdk-0.1.4.dist-info/RECORD
