Metadata-Version: 2.4
Name: aether-framework-sdk
Version: 0.1.4
Summary: Python SDK for Aether workflow engine
License: Apache-2.0
Project-URL: Homepage, https://github.com/your-org/aether
Project-URL: Repository, https://github.com/your-org/aether
Project-URL: Issues, https://github.com/your-org/aether/issues
Classifier: Development Status :: 3 - Alpha
Classifier: Intended Audience :: Developers
Classifier: License :: OSI Approved :: Apache Software License
Classifier: Programming Language :: Python :: 3
Classifier: Programming Language :: Python :: 3.10
Classifier: Programming Language :: Python :: 3.11
Classifier: Programming Language :: Python :: 3.12
Requires-Python: >=3.10
Requires-Dist: aiohttp>=3.9.0
Requires-Dist: grpcio>=1.59.0
Requires-Dist: grpcio-tools>=1.59.0
Provides-Extra: dev
Requires-Dist: pytest; extra == "dev"
Requires-Dist: pytest-asyncio; extra == "dev"
Requires-Dist: black; extra == "dev"
Requires-Dist: isort; extra == "dev"
Requires-Dist: mypy; extra == "dev"
